Workbook

Sheet - AYUDA -
B4: Ayuda

Sheet Precios 
B5: Comparación de Precios entre diferentes proveedores
B6: Ingresa en la tabla los productos, los proveedores y sus precios
J7: ESTADÍSTICAS POR PRODUCTO
B8: PRODUCTO | C8: CANTIDAD | D8: Mercado Libre | E8: speedlogic | F8: pcware | G8: amazon | H8: clones y perifericos | I8: pcstorecolombia | J8: PRECIO MÁS BAJO | K8: PRECIO PROMEDIO | L8: PRECIO MÁS ALTO
B9: memoria ram 8Gb | C9: 2 | D9: 77000 | E9: 103000 | F9: 149900 | G9: 40000 | H9: 80000 | I9: 115000 | J9: =MIN('Precios '!$D9:$I9) -> 40000 | K9: =IFERROR(AVERAGE('Precios '!$D9:$I9),0) -> 94150 | L9: =MAX('Precios '!$D9:$I9) -> 149900
B10: gabinete | C10: 1 | D10: 190000 | E10: 301000 | F10: 115000 | G10: 284000 | H10: 500000 | I10: 480000 | J10: =MIN('Precios '!$D10:$I10) -> 115000 | K10: =IFERROR(AVERAGE('Precios '!$D10:$I10),0) -> 311666.67 | L10: =MAX('Precios '!$D10:$I10) -> 500000
B11: placa base | C11: 1 | D11: 709000 | E11: 429000 | F11: 500000 | G11: 364000 | H11: 480000 | I11: 700000 | J11: =MIN('Precios '!$D11:$I11) -> 364000 | K11: =IFERROR(AVERAGE('Precios '!$D11:$I11),0) -> 530333.33 | L11: =MAX('Precios '!$D11:$I11) -> 709000
B12: procesador | C12: 1 | D12: 2500000 | E12: 2000000 | F12: 1200000 | G12: 689000 | H12: 856000 | I12: 700000 | J12: =MIN('Precios '!$D12:$I12) -> 689000 | K12: =IFERROR(AVERAGE('Precios '!$D12:$I12),0) -> 1324166.7 | L12: =MAX('Precios '!$D12:$I12) -> 2500000
B13: memoria ssd de 500gb | C13: 1 | D13: 900000 | E13: 800000 | F13: 700000 | G13: 170000 | H13: 700000 | I13: 900000 | J13: =MIN('Precios '!$D13:$I13) -> 170000 | K13: =IFERROR(AVERAGE('Precios '!$D13:$I13),0) -> 695000 | L13: =MAX('Precios '!$D13:$I13) -> 900000
B14: fuente de poder | C14: 1 | D14: 1500000 | E14: 700000 | F14: 600000 | G14: 364000 | H14: 800000 | I14: 400000 | J14: =MIN('Precios '!$D14:$I14) -> 364000 | K14: =IFERROR(AVERAGE('Precios '!$D14:$I14),0) -> 727333.33 | L14: =MAX('Precios '!$D14:$I14) -> 1500000
B15: monitor | C15: 1 | D15: 1100000 | E15: 1000000 | F15: 670000 | G15: 440000 | H15: 800000 | I15: 1050000 | J15: =MIN('Precios '!$D15:$I15) -> 440000 | K15: =IFERROR(AVERAGE('Precios '!$D15:$I15),0) -> 843333.33 | L15: =MAX('Precios '!$D15:$I15) -> 1100000
B16: teclado | C16: 1 | D16: 500000 | E16: 450000 | F16: 300000 | G16: 250000 | H16: 200000 | I16: 200000 | J16: =MIN('Precios '!$D16:$I16) -> 200000 | K16: =IFERROR(AVERAGE('Precios '!$D16:$I16),0) -> 316666.67 | L16: =MAX('Precios '!$D16:$I16) -> 500000
B17: mause | C17: 1 | D17: 25000 | E17: 30000 | F17: 100000 | G17: 46000 | H17: 70000 | I17: 45000 | J17: =MIN('Precios '!$D17:$I17) -> 25000 | K17: =IFERROR(AVERAGE('Precios '!$D17:$I17),0) -> 52666.667 | L17: =MAX('Precios '!$D17:$I17) -> 100000
B18: sistema de refrigeración para pc | C18: 1 | D18: 1100000 | E18: 1000000 | F18: 998000 | G18: 469000 | H18: 720000 | I18: 680000 | J18: =MIN('Precios '!$D18:$I18) -> 469000 | K18: =IFERROR(AVERAGE('Precios '!$D18:$I18),0) -> 827833.33 | L18: =MAX('Precios '!$D18:$I18) -> 1100000
J19: =MIN('Precios '!$D19:$I19) -> 0 | K19: =IFERROR(AVERAGE('Precios '!$D19:$I19),0) -> 0 | L19: =MAX('Precios '!$D19:$I19) -> 0
J20: =MIN('Precios '!$D20:$I20) -> 0 | K20: =IFERROR(AVERAGE('Precios '!$D20:$I20),0) -> 0 | L20: =MAX('Precios '!$D20:$I20) -> 0
J21: =MIN('Precios '!$D21:$I21) -> 0 | K21: =IFERROR(AVERAGE('Precios '!$D21:$I21),0) -> 0 | L21: =MAX('Precios '!$D21:$I21) -> 0
J22: =MIN('Precios '!$D22:$I22) -> 0 | K22: =IFERROR(AVERAGE('Precios '!$D22:$I22),0) -> 0 | L22: =MAX('Precios '!$D22:$I22) -> 0
J23: =MIN('Precios '!$D23:$I23) -> 0 | K23: =IFERROR(AVERAGE('Precios '!$D23:$I23),0) -> 0 | L23: =MAX('Precios '!$D23:$I23) -> 0
J24: =MIN('Precios '!$D24:$I24) -> 0 | K24: =IFERROR(AVERAGE('Precios '!$D24:$I24),0) -> 0 | L24: =MAX('Precios '!$D24:$I24) -> 0
J25: =MIN('Precios '!$D25:$I25) -> 0 | K25: =IFERROR(AVERAGE('Precios '!$D25:$I25),0) -> 0 | L25: =MAX('Precios '!$D25:$I25) -> 0
B26: Total | D26: =ROUND(SUMPRODUCT('Precios '!$C$9:$C$25,'Precios '!$E$9:$E$25),2) -> 6916000 | E26: =ROUND(SUMPRODUCT('Precios '!$C$9:$C$25,'Precios '!$E$9:$E$25),2) -> 6916000 | F26: =ROUND(SUMPRODUCT('Precios '!$C$9:$C$25,'Precios '!$F$9:$F$25),2) -> 5482800 | G26: =ROUND(SUMPRODUCT('Precios '!$C$9:$C$25,'Precios '!$G$9:$G$25),2) -> 3156000 | H26: =ROUND(SUMPRODUCT('Precios '!$C$9:$C$25,'Precios '!$H$9:$H$25),2) -> 5286000 | I26: =ROUND(SUMPRODUCT('Precios '!$C$9:$C$25,'Precios '!$I$9:$I$25),2) -> 5385000
B29: DATOS ADICIONALES | D29: Mercado Libre | E29: speedlogic | F29: amazon | G29: pcware | H29: clones y perifericos | I29: pcstorecolombia
B30: TIEMPO DE ENTREGA (DÍAS) | D30: Horas de dia los 7 dias de la semana | E30: de 3 a 5 minutos | F30: 3 a 10 dias habiles | G30: entrega de 2 dias habiles | H30: 1 a 5 dias habiles | I30: 5 dias laborales
B31: COSTO DE ENVÍO | D31: 0 | E31: $ 7.055 | F31: 40000 | G31: 0 | H31: $295.39 | I31: 0
B32: FORMAS DE PAGO
D34: contado | E34: contado | F34: contado | G34: contado | H34: contado | I34: contado

Sheet Precios  (2)
B5: Comparación de Precios entre diferentes proveedores
B6: Ingresa en la tabla los productos, los proveedores y sus precios
J7: ESTADÍSTICAS POR PRODUCTO
B8: PRODUCTO | C8: CANTIDAD | D8: PROVEEDOR 1 | E8: PROVEEDOR 2 | F8: PROVEEDOR 3 | G8: PROVEEDOR 4 | H8: PROVEEDOR 5 | I8: PROVEEDOR 6 | J8: PRECIO MÁS BAJO | K8: PRECIO PROMEDIO | L8: PRECIO MÁS ALTO
B9: ='[1]Portatil Nosotros'!$D$8 -> #REF! | C9: 3 | D9: ='[1]Monitor Nosotros'!$H$8*3 -> #REF! | E9: ='[1]Portatil Nosotros'!$H$9*3 -> #REF! | F9: ='[1]Monitor Nosotros'!$H$10*3 -> #REF! | J9: =MIN('Precios (2)'!$D9:$I9) -> #REF! | K9: =IFERROR(AVERAGE('Precios (2)'!$D9:$I9),0) -> 0 | L9: =MAX('Precios (2)'!$D9:$I9) -> #REF!
B10: ='[1]Monitor Nosotros'!$D$8 -> #REF! | C10: 3 | D10: ='[1]Monitor Nosotros'!$H$8*3 -> #REF! | E10: ='[1]Monitor Nosotros'!$H$9*3 -> #REF! | F10: ='[1]Monitor Nosotros'!$H$10*3 -> #REF! | J10: =MIN('Precios (2)'!$D10:$I10) -> #REF! | K10: =IFERROR(AVERAGE('Precios (2)'!$D10:$I10),0) -> 0 | L10: =MAX('Precios (2)'!$D10:$I10) -> #REF!
B11: ='[1] Disco mecanico Nosotros'!$D$8 -> #REF! | C11: 3 | D11: ='[1] Disco mecanico Nosotros'!$H$8*3 -> #REF! | E11: ='[1] Disco mecanico Nosotros'!$H$9*3 -> #REF! | F11: ='[1] Disco mecanico Nosotros'!$H$10*3 -> #REF! | J11: =MIN('Precios (2)'!$D11:$I11) -> #REF! | K11: =IFERROR(AVERAGE('Precios (2)'!$D11:$I11),0) -> 0 | L11: =MAX('Precios (2)'!$D11:$I11) -> #REF!
B12: ='[1] ram nosotros'!$D$8 -> #REF! | C12: 3 | D12: ='[1] ram nosotros'!$H$8*3 -> #REF! | E12: ='[1] ram nosotros'!$H$9*3 -> #REF! | F12: ='[1] ram nosotros'!$H$10*3 -> #REF! | J12: =MIN('Precios (2)'!$D12:$I12) -> #REF! | K12: =IFERROR(AVERAGE('Precios (2)'!$D12:$I12),0) -> 0 | L12: =MAX('Precios (2)'!$D12:$I12) -> #REF!
B13: ='[1] Servidor Nosotros'!$D$8 -> #REF! | C13: 3 | D13: ='[1] Servidor Nosotros'!$H$8*3 -> #REF! | E13: ='[1] Servidor Nosotros'!$H$9*3 -> #REF! | F13: ='[1] Servidor Nosotros'!$H$10*3 -> #REF! | J13: =MIN('Precios (2)'!$D13:$I13) -> #REF! | K13: =IFERROR(AVERAGE('Precios (2)'!$D13:$I13),0) -> 0 | L13: =MAX('Precios (2)'!$D13:$I13) -> #REF!
B14: ='[1]Tarjeta de video nosotros'!$D$8 -> #REF! | C14: 3 | D14: ='[1]Tarjeta de video nosotros'!$H$8*3 -> #REF! | E14: ='[1]Tarjeta de video nosotros'!$H$9*3 -> #REF! | F14: ='[1]Tarjeta de video nosotros'!$H$10*3 -> #REF! | J14: =MIN('Precios (2)'!$D14:$I14) -> #REF! | K14: =IFERROR(AVERAGE('Precios (2)'!$D14:$I14),0) -> 0 | L14: =MAX('Precios (2)'!$D14:$I14) -> #REF!
B15: ='[1]Procesador Nosotros'!$D$8 -> #REF! | C15: 3 | D15: ='[1]Procesador Nosotros'!$G$8*3 -> #REF! | E15: ='[1]Procesador Nosotros'!$H$9*3 -> #REF! | F15: ='[1]Procesador Nosotros'!$H$10*3 -> #REF! | J15: =MIN('Precios (2)'!$D15:$I15) -> #REF! | K15: =IFERROR(AVERAGE('Precios (2)'!$D15:$I15),0) -> 0 | L15: =MAX('Precios (2)'!$D15:$I15) -> #REF!
B16: ='[1]Teclado Admin'!$D$8 -> #REF! | C16: 3 | D16: ='[1]Teclado nosostros '!$H$8*3 -> #REF! | E16: ='[1]Teclado nosostros '!$H$9*3 -> #REF! | F16: ='[1]Teclado nosostros '!$H$10*3 -> #REF! | J16: =MIN('Precios (2)'!$D16:$I16) -> #REF! | K16: =IFERROR(AVERAGE('Precios (2)'!$D16:$I16),0) -> 0 | L16: =MAX('Precios (2)'!$D16:$I16) -> #REF!
B17: ='[1]Mause Admin'!$D$8 -> #REF! | C17: 3 | D17: ='[1]Muse nosotros'!$H$8*3 -> #REF! | E17: ='[1]Muse nosotros'!$H$9*3 -> #REF! | F17: ='[1]Muse nosotros'!$H$10*3 -> #REF! | J17: =MIN('Precios (2)'!$D17:$I17) -> #REF! | K17: =IFERROR(AVERAGE('Precios (2)'!$D17:$I17),0) -> 0 | L17: =MAX('Precios (2)'!$D17:$I17) -> #REF!
B18: ='[1]software licencia'!$D$8 -> #REF! | C18: 3 | D18: ='[1]software licencia'!$H$8*3 -> #REF! | E18: ='[1]software licencia'!$H$9*3 -> #REF! | F18: ='[1]software licencia'!$H$10*3 -> #REF! | J18: =MIN('Precios (2)'!$D18:$I18) -> #REF! | K18: =IFERROR(AVERAGE('Precios (2)'!$D18:$I18),0) -> 0 | L18: =MAX('Precios (2)'!$D18:$I18) -> #REF!
B19: ='[1]licencia visual'!$D$8 -> #REF! | C19: 3 | D19: ='[1]licencia visual'!$H$8*3 -> #REF! | E19: ='[1]licencia visual'!$H$9*3 -> #REF! | F19: ='[1]licencia visual'!$H$10*3 -> #REF! | J19: =MIN('Precios (2)'!$D19:$I19) -> #REF! | K19: =IFERROR(AVERAGE('Precios (2)'!$D19:$I19),0) -> 0 | L19: =MAX('Precios (2)'!$D19:$I19) -> #REF!
B20: ='[1]windows 11 licencia'!$D$8 -> #REF! | C20: 3 | D20: ='[1]licencia visual'!$H$8*3 -> #REF! | E20: ='[1]licencia visual'!$H$9*3 -> #REF! | F20: ='[1]licencia visual'!$H$10*3 -> #REF! | J20: =MIN('Precios (2)'!$D20:$I20) -> #REF! | K20: =IFERROR(AVERAGE('Precios (2)'!$D20:$I20),0) -> 0 | L20: =MAX('Precios (2)'!$D20:$I20) -> #REF!
B21: ='[1]licencia SQL'!$D$8 -> #REF! | C21: 3 | D21: ='[1]licencia SQL'!$H$8*3 -> #REF! | E21: ='[1]licencia SQL'!$H$9*3 -> #REF! | F21: ='[1]windows 11 licencia'!$H$10*3 -> #REF! | J21: =MIN('Precios (2)'!$D21:$I21) -> #REF! | K21: =IFERROR(AVERAGE('Precios (2)'!$D21:$I21),0) -> 0 | L21: =MAX('Precios (2)'!$D21:$I21) -> #REF!
J22: =MIN('Precios (2)'!$D22:$I22) -> 0 | K22: =IFERROR(AVERAGE('Precios (2)'!$D22:$I22),0) -> 0 | L22: =MAX('Precios (2)'!$D22:$I22) -> 0
J23: =MIN('Precios (2)'!$D23:$I23) -> 0 | K23: =IFERROR(AVERAGE('Precios (2)'!$D23:$I23),0) -> 0 | L23: =MAX('Precios (2)'!$D23:$I23) -> 0
J24: =MIN('Precios (2)'!$D24:$I24) -> 0 | K24: =IFERROR(AVERAGE('Precios (2)'!$D24:$I24),0) -> 0 | L24: =MAX('Precios (2)'!$D24:$I24) -> 0
B25: Total | D25: =ROUND(SUMPRODUCT('Precios (2)'!$C$9:$C$24,'Precios (2)'!$D$9:$D$24),2) -> #REF! | E25: =ROUND(SUMPRODUCT('Precios (2)'!$C$9:$C$24,'Precios (2)'!$E$9:$E$24),2) -> #REF! | F25: =ROUND(SUMPRODUCT('Precios (2)'!$C$9:$C$24,'Precios (2)'!$F$9:$F$24),2) -> #REF! | G25: =ROUND(SUMPRODUCT('Precios (2)'!$C$9:$C$24,'Precios (2)'!$G$9:$G$24),2) -> 0 | H25: =ROUND(SUMPRODUCT('Precios (2)'!$C$9:$C$24,'Precios (2)'!$H$9:$H$24),2) -> 0 | I25: =ROUND(SUMPRODUCT('Precios (2)'!$C$9:$C$24,'Precios (2)'!$I$9:$I$24),2) -> 0
B28: DATOS ADICIONALES
B29: TIEMPO DE ENTREGA (DÍAS)
B30: COSTO DE ENVÍO
B31: FORMAS DE PAGO

Sheet Soporte
B7: Almendras | C7: 1 | D7: 498 | E7: 420 | F7: 450 | G7: 230 | H7: 600 | I7: 520
B8: Nueces | C8: 2 | D8: 450 | E8: 220 | F8: 405 | G8: 495 | H8: 540 | I8: 200
B9: Pistachos | C9: 2 | D9: 650 | E9: 620 | F9: 666 | G9: 400 | H9: 648 | I9: 452.4
B10: Pecán | C10: 1 | D10: 585 | E10: 558 | F10: 320 | G10: 360 | H10: 583.2 | I10: 407.16
B11: Bananas | C11: 3 | D11: 526.5 | E11: 502.2 | F11: 539.46 | G11: 300 | H11: 500 | I11: 366.44
B12: Pasas | C12: 1 | D12: 473.8 | E12: 200 | F12: 485.51 | G12: 291.6 | H12: 270 | I12: 220
D19: 30 | E19: 10 | F19: 15 | G19: 15 | H19: 15 | I19: 10
D20: 10 | E20: 10 | F20: 10 | G20: Gratis | H20: 5 | I20: Gratis
D21: Efvo | E21: Efvo | F21: Mercado Pago | G21: Efectivo | H21: Mercado Pago | I21: Mercado Pago
D22: Tarjeta | E22: Tarjeta | F22: Tarjeta cuotas | G22: Mercado Pago | H22: Tarjeta cuotas | I22: Tarjeta cuotas
B28: Piñones | C28: 1 | D28: 340 | E28: 330 | F28: 440 | G28: 400 | H28: 320 | I28: 330
B29: Cranberries | C29: 1 | D29: 220 | E29: 230 | F29: 240 | G29: 220 | H29: 219 | I29: 218
B30: Castañas | C30: 2 | D30: 560 | E30: 580 | F30: 550 | G30: 520 | H30: 551 | I30: 550
B35: China Co
B36: 250
B37: 440
B38: 440
B39: 350
B40: 420
B41: 199
